README.md
setup.cfg
setup.py
robotcloud/__init__.py
robotcloud/api.py
robotcloud/authenticator.py
robotcloud/constants.py
robotcloud/exceptions.py
robotcloud.egg-info/PKG-INFO
robotcloud.egg-info/SOURCES.txt
robotcloud.egg-info/dependency_links.txt
robotcloud.egg-info/requires.txt
robotcloud.egg-info/top_level.txt
robotcloud/endpoints/__init__.py
robotcloud/endpoints/configurationtypes.py
robotcloud/endpoints/devices.py
robotcloud/endpoints/locations.py
robotcloud/endpoints/login.py
robotcloud/endpoints/organizations.py
robotcloud/endpoints/projects.py
robotcloud/endpoints/services.py
robotcloud/endpoints/services_data.py
robotcloud/endpoints/subsystems.py
robotcloud/endpoints/tags.py
robotcloud/endpoints/users.py
robotcloud/utils/__init__.py
robotcloud/utils/paginated_response.py
robotcloud/utils/pagination.py