Metadata-Version: 2.1
Name: robotcloud
Version: 0.1.2
Summary: Client to interact with robotcloud API from a python project.
Home-page: https://github.com/robotmallorca/sw.module.python.robotcloud.client
Author: Bernat Galmés Rubert
Author-email: bernat.galmes@robotbas.com
License: UNKNOWN
Keywords: client robotcloud
Platform: UNKNOWN
